MANIFEST.in
README.txt
setup.cfg
setup.py
SimpleSite.egg-info/PKG-INFO
SimpleSite.egg-info/SOURCES.txt
SimpleSite.egg-info/dependency_links.txt
SimpleSite.egg-info/entry_points.txt
SimpleSite.egg-info/not-zip-safe
SimpleSite.egg-info/paster_plugins.txt
SimpleSite.egg-info/requires.txt
SimpleSite.egg-info/top_level.txt
simplesite/__init__.py
simplesite/websetup.py
simplesite/config/__init__.py
simplesite/config/deployment.ini_tmpl
simplesite/config/environment.py
simplesite/config/middleware.py
simplesite/config/routing.py
simplesite/controllers/__init__.py
simplesite/controllers/account.py
simplesite/controllers/comment.py
simplesite/controllers/error.py
simplesite/controllers/nav.py
simplesite/controllers/page.py
simplesite/controllers/section.py
simplesite/controllers/tag.py
simplesite/lib/__init__.py
simplesite/lib/app_globals.py
simplesite/lib/auth.py
simplesite/lib/base.py
simplesite/lib/helpers.py
simplesite/lib/middleware.py
simplesite/model/__init__.py
simplesite/model/meta.py
simplesite/public/css/main.css
simplesite/public/yui/2.6.0/LICENSE.txt
simplesite/public/yui/2.6.0/animation/animation-min.js
simplesite/public/yui/2.6.0/assets/skins/sam/blankimage.png
simplesite/public/yui/2.6.0/assets/skins/sam/editor-sprite-active.gif
simplesite/public/yui/2.6.0/assets/skins/sam/editor-sprite.gif
simplesite/public/yui/2.6.0/assets/skins/sam/skin.css
simplesite/public/yui/2.6.0/assets/skins/sam/sprite.png
simplesite/public/yui/2.6.0/connection/connection-min.js
simplesite/public/yui/2.6.0/container/container_core-min.js
simplesite/public/yui/2.6.0/editor/simpleeditor-min.js
simplesite/public/yui/2.6.0/element/element-beta-min.js
simplesite/public/yui/2.6.0/json/json-min.js
simplesite/public/yui/2.6.0/reset-fonts-grids/reset-fonts-grids.css
simplesite/public/yui/2.6.0/yahoo-dom-event/yahoo-dom-event.js
simplesite/templates/base/index.html
simplesite/templates/component/navigation.html
simplesite/templates/derived/account/signedin.html
simplesite/templates/derived/account/signedout.html
simplesite/templates/derived/account/signin.html
simplesite/templates/derived/comment/deleted.html
simplesite/templates/derived/comment/edit.html
simplesite/templates/derived/comment/fields.html
simplesite/templates/derived/comment/list.html
