Metadata-Version: 1.0
Name: SimpleSite
Version: 0.3.0
Summary: A simple website application written as a demonstration of Pylons for the Definitive Guide to Pylons
Home-page: http://pylonsbook.com
Author: James Gardner
Author-email: feeback@pylonsbook.com
License: BSD, see the simplesite/public/yui/2.6.0/LICENSE.txt file for details.
Keywords: pylons simple site book example
Platform: UNKNOWN
